shallowgibbs/__init__.py
shallowgibbs/doublebackpropagation.py
shallowgibbs_doublebackpropagation-1.0.3.dist-info/METADATA
shallowgibbs_doublebackpropagation-1.0.3.dist-info/WHEEL
shallowgibbs_doublebackpropagation-1.0.3.dist-info/entry_points.txt
shallowgibbs_doublebackpropagation-1.0.3.dist-info/top_level.txt
shallowgibbs_doublebackpropagation-1.0.3.dist-info/RECORD
