Metadata-Version: 2.1
Name: shallowgibbs-doublebackpropagation
Version: 1.0.3
Summary: Shallow Gibbs Double Backpropagation
Home-page: https://github.com/kgalahassa/shallowgibbs-doublebackpropagation
Author: Alejandro, Murua and Alahassa, Nonvikan Karl-Augustt
Author-email: alahassa@dms.umontreal.ca
License: GNU General Public License v3.0
Keywords: Shallow Gibbs,Neural Network,Double Backpropagation
Platform: UNKNOWN
Classifier: Programming Language :: Python :: 3
Classifier: License :: OSI Approved :: GNU Lesser General Public License v3 (LGPLv3)
Classifier: Operating System :: OS Independent
Requires-Dist: scipy (==1.6.2)
Requires-Dist: tensorflow (==1.15.0)
Requires-Dist: pandas (==1.1.3)
Requires-Dist: numpy (==1.19.2)
Requires-Dist: joblib (==1.0.1)
Requires-Dist: scikit-learn (==0.24.2)
